sxdump-2.0.1.dist-info/top_level.txt
sxdump-2.0.1.dist-info/metadata.json
sxdump-2.0.1.dist-info/METADATA
sxdump-2.0.1.dist-info/entry_points.txt
sxdump-2.0.1.dist-info/RECORD
sxdump-2.0.1.dist-info/WHEEL
sxdump-2.0.1.dist-info/DESCRIPTION.rst
sxdump/createvol.py
sxdump/configreader.py
sxdump/sxdump.py
sxdump/__init__.py
sxdump/makecmds.py
sxdump/getvolinfo.py
